filepy/__init__.py
filepy/analyse_helper.py
filepy/arff_reader.py
filepy/arff_writer.py
filepy/csv_reader.py
filepy/csv_writer.py
filepy/dto.py
filepy/file_converter.py
filepy-0.17.dist-info/LICENSE
filepy-0.17.dist-info/METADATA
filepy-0.17.dist-info/WHEEL
filepy-0.17.dist-info/top_level.txt
filepy-0.17.dist-info/RECORD
