Metadata-Version: 2.1
Name: filepy
Version: 0.17
Summary: File converter to different extensions
Home-page: https://github.com/KordianD/filepy
Author: KordianD
Author-email: not_valid@gmail.com
License: UNKNOWN
Keywords: file,convert,extensions,csv,arff
Platform: UNKNOWN
Classifier: Programming Language :: Python :: 3
Classifier: License :: OSI Approved :: MIT License
